setup.py
rtorrentinotify/__init__.py
rtorrentinotify/core.py
rtorrentinotify.egg-info/PKG-INFO
rtorrentinotify.egg-info/SOURCES.txt
rtorrentinotify.egg-info/dependency_links.txt
rtorrentinotify.egg-info/entry_points.txt
rtorrentinotify.egg-info/requires.txt
rtorrentinotify.egg-info/top_level.txt