Metadata-Version: 1.0
Name: rtorrentinotify
Version: 0.0.2
Summary: Watches a directory for torrents and moves them to the actual rtorrent watch dir
Home-page: UNKNOWN
Author: eayin2
Author-email: eayin2@gmail.com
License: UNKNOWN
Platform: UNKNOWN
